dbis_relational_algebra-1.1.8.dist-info/licenses/LICENSE
relational_algebra/__init__.py
relational_algebra/formulas/Formula.py
relational_algebra/formulas/__init__.py
relational_algebra/formulas/atoms/Equals.py
relational_algebra/formulas/atoms/GreaterEquals.py
relational_algebra/formulas/atoms/GreaterThan.py
relational_algebra/formulas/atoms/LessEquals.py
relational_algebra/formulas/atoms/LessThan.py
relational_algebra/formulas/atoms/__init__.py
relational_algebra/formulas/conenctives/And.py
relational_algebra/formulas/conenctives/Not.py
relational_algebra/formulas/conenctives/Or.py
relational_algebra/formulas/conenctives/__init__.py
relational_algebra/operators/CrossProduct.py
relational_algebra/operators/Difference.py
relational_algebra/operators/Division.py
relational_algebra/operators/Intersection.py
relational_algebra/operators/LeftSemiJoin.py
relational_algebra/operators/NaturalJoin.py
relational_algebra/operators/Operator.py
relational_algebra/operators/Projection.py
relational_algebra/operators/Relation.py
relational_algebra/operators/Rename.py
relational_algebra/operators/RightSemiJoin.py
relational_algebra/operators/Selection.py
relational_algebra/operators/ThetaJoin.py
relational_algebra/operators/Union.py
relational_algebra/operators/__init__.py
dbis_relational_algebra-1.1.8.dist-info/METADATA
dbis_relational_algebra-1.1.8.dist-info/WHEEL
dbis_relational_algebra-1.1.8.dist-info/top_level.txt
dbis_relational_algebra-1.1.8.dist-info/RECORD
